{
  "gitSyncId": "65b2c8ac18b3ec7241c8bd7d_66204272616409113a09fe11",
  "id": "Page1_update_qual_override",
  "pluginId": "restapi-plugin",
  "pluginType": "API",
  "unpublishedAction": {
    "actionConfiguration": {
      "autoGeneratedHeaders": [
        {
          "key": "content-type",
          "value": "application/json"
        }
      ],
      "body": "{\"application\":{\n\t\"id\": \"{{ appsmith.URL.queryParams.application || DEBUG_appid.text }}\",\n\t\"qualifyingperson\": {\n\t\"name\":\"{{List1Copy.triggeredItem.name}}\",\n\t\"id\": {{List1Copy.triggeredItem.value}}\n}}}",
      "bodyFormData": [],
      "encodeParamsToggle": true,
      "formData": {
        "apiContentType": "none"
      },
      "headers": [
        {
          "key": "appid",
          "value": "{{ appsmith.URL.queryParams.application || DEBUG_appid.text }}"
        }
      ],
      "httpMethod": "POST",
      "httpVersion": "HTTP11",
      "paginationType": "NONE",
      "path": "/v1/ccims/ccdsd/hau/update",
      "pluginSpecifiedTemplates": [
        {
          "value": true
        }
      ],
      "queryParameters": [],
      "timeoutInMillisecond": 10000
    },
    "confirmBeforeExecute": false,
    "datasource": {
      "datasourceConfiguration": {
        "url": "https://api.chillwireless.com"
      },
      "isAutoGenerated": false,
      "name": "DEFAULT_REST_DATASOURCE",
      "pluginId": "restapi-plugin"
    },
    "dynamicBindingPathList": [
      {
        "key": "headers[0].value"
      },
      {
        "key": "body"
      }
    ],
    "executeOnLoad": false,
    "name": "update_qual_override",
    "pageId": "Page1",
    "userSetOnLoad": false
  }
}